<?xml version="1.0" encoding="UTF-8"?>
<!-- generated: 2025-06-25T23:39:34+08:00 -->
<!-- generated by: qiujie [??] -->
<adag xmlns="http://pegasus.isi.edu/schema/DAX" xmlns:xsi="http://www.w3.org/2001/XMLSchema-instance" xsi:schemaLocation="http://pegasus.isi.edu/schema/DAX http://pegasus.isi.edu/schema/dax-2.1.xsd" version="2.1" count="1" index="0" name="test" jobCount="25" fileCount="0" childCount="24">
<!-- part 1: list of all referenced files (may be empty) -->
<!-- part 2: definition of all jobs (at least one) -->
  <job id="ID00000" namespace="CyberShake" name="ZipPSA" version="1.0" runtime="0.09">
    <uses file="PeakVals_FFI_0_1_ID00003.bsa" link="input" register="false" transfer="false" optional="false" type="data" size="216"/>
    <uses file="PeakVals_FFI_0_1_ID00005.bsa" link="input" register="false" transfer="false" optional="false" type="data" size="216"/>
    <uses file="PeakVals_FFI_0_1_ID00007.bsa" link="input" register="false" transfer="false" optional="false" type="data" size="216"/>
    <uses file="PeakVals_FFI_0_1_ID00009.bsa" link="input" register="false" transfer="false" optional="false" type="data" size="216"/>
    <uses file="PeakVals_FFI_0_1_ID00011.bsa" link="input" register="false" transfer="false" optional="false" type="data" size="216"/>
    <uses file="PeakVals_FFI_0_1_ID00013.bsa" link="input" register="false" transfer="false" optional="false" type="data" size="216"/>
    <uses file="PeakVals_FFI_0_1_ID00015.bsa" link="input" register="false" transfer="false" optional="false" type="data" size="216"/>
    <uses file="PeakVals_FFI_0_1_ID00017.bsa" link="input" register="false" transfer="false" optional="false" type="data" size="216"/>
    <uses file="PeakVals_FFI_0_1_ID00019.bsa" link="input" register="false" transfer="false" optional="false" type="data" size="216"/>
    <uses file="PeakVals_FFI_0_1_ID00021.bsa" link="input" register="false" transfer="false" optional="false" type="data" size="216"/>
    <uses file="PeakVals_FFI_0_1_ID00023.bsa" link="input" register="false" transfer="false" optional="false" type="data" size="216"/>
    <uses file="Cybershake_PSA.zip" link="output" register="true" transfer="true" optional="false" type="data" size="246"/>
  </job>
  <job id="ID00001" namespace="CyberShake" name="ZipSeis" version="1.0" runtime="0.08">
    <uses file="Seismogram_FFI_0_1_ID00003.grm" link="input" register="false" transfer="false" optional="false" type="data" size="24000"/>
    <uses file="Seismogram_FFI_0_1_ID00005.grm" link="input" register="false" transfer="false" optional="false" type="data" size="24000"/>
    <uses file="Seismogram_FFI_0_1_ID00007.grm" link="input" register="false" transfer="false" optional="false" type="data" size="24000"/>
    <uses file="Seismogram_FFI_0_1_ID00009.grm" link="input" register="false" transfer="false" optional="false" type="data" size="24000"/>
    <uses file="Seismogram_FFI_0_1_ID00011.grm" link="input" register="false" transfer="false" optional="false" type="data" size="24000"/>
    <uses file="Seismogram_FFI_0_1_ID00013.grm" link="input" register="false" transfer="false" optional="false" type="data" size="24000"/>
    <uses file="Seismogram_FFI_0_1_ID00015.grm" link="input" register="false" transfer="false" optional="false" type="data" size="24000"/>
    <uses file="Seismogram_FFI_0_1_ID00017.grm" link="input" register="false" transfer="false" optional="false" type="data" size="24000"/>
    <uses file="Seismogram_FFI_0_1_ID00019.grm" link="input" register="false" transfer="false" optional="false" type="data" size="24000"/>
    <uses file="Seismogram_FFI_0_1_ID00021.grm" link="input" register="false" transfer="false" optional="false" type="data" size="24000"/>
    <uses file="Seismogram_FFI_0_1_ID00023.grm" link="input" register="false" transfer="false" optional="false" type="data" size="24000"/>
    <uses file="Cybershake_Seismograms.zip" link="output" register="true" transfer="true" optional="false" type="data" size="18799"/>
  </job>
  <job id="ID00002" namespace="CyberShake" name="ExtractSGT" version="1.0" runtime="130.42">
    <uses file="FFI_0_1_fx.sgt" link="input" register="true" transfer="true" optional="false" type="data" size="19800234657"/>
    <uses file="FFI_0_1_fy.sgt" link="input" register="true" transfer="true" optional="false" type="data" size="19800234657"/>
    <uses file="FFI_0_1_subfx.sgt" link="output" register="false" transfer="false" optional="false" type="data" size="259424202"/>
    <uses file="FFI_0_1_subfy.sgt" link="output" register="false" transfer="false" optional="false" type="data" size="259424202"/>
    <uses file="FFI_0_1_txt.variation-s06925-h01869" link="input" register="true" transfer="true" optional="false" type="data" size="2663547"/>
  </job>
  <job id="ID00003" namespace="CyberShake" name="SeismogramSynthesis" version="1.0" runtime="61.07">
    <uses file="FFI_0_1_txt.variation-s04028-h03686" link="input" register="true" transfer="true" optional="false" type="data" size="3388357"/>
    <uses file="FFI_0_1_subfx.sgt" link="input" register="false" transfer="false" optional="false" type="data" size="259424202"/>
    <uses file="FFI_0_1_subfy.sgt" link="input" register="false" transfer="false" optional="false" type="data" size="259424202"/>
    <uses file="Seismogram_FFI_0_1_ID00003.grm" link="output" register="false" transfer="false" optional="false" type="data" size="24000"/>
  </job>
  <job id="ID00004" namespace="CyberShake" name="PeakValCalcOkaya" version="1.0" runtime="0.67">
    <uses file="Seismogram_FFI_0_1_ID00003.grm" link="input" register="false" transfer="false" optional="false" type="data" size="24000"/>
    <uses file="PeakVals_FFI_0_1_ID00003.bsa" link="output" register="false" transfer="false" optional="false" type="data" size="216"/>
  </job>
  <job id="ID00005" namespace="CyberShake" name="SeismogramSynthesis" version="1.0" runtime="30.29">
    <uses file="FFI_0_1_txt.variation-s07771-h02343" link="input" register="true" transfer="true" optional="false" type="data" size="2878273"/>
    <uses file="FFI_0_1_subfx.sgt" link="input" register="false" transfer="false" optional="false" type="data" size="144349576"/>
    <uses file="FFI_0_1_subfy.sgt" link="input" register="false" transfer="false" optional="false" type="data" size="144349576"/>
    <uses file="Seismogram_FFI_0_1_ID00005.grm" link="output" register="false" transfer="false" optional="false" type="data" size="24000"/>
  </job>
  <job id="ID00006" namespace="CyberShake" name="PeakValCalcOkaya" version="1.0" runtime="0.89">
    <uses file="Seismogram_FFI_0_1_ID00005.grm" link="input" register="false" transfer="false" optional="false" type="data" size="24000"/>
    <uses file="PeakVals_FFI_0_1_ID00005.bsa" link="output" register="false" transfer="false" optional="false" type="data" size="216"/>
  </job>
  <job id="ID00007" namespace="CyberShake" name="SeismogramSynthesis" version="1.0" runtime="52.26">
    <uses file="FFI_0_1_txt.variation-s03518-h06886" link="input" register="true" transfer="true" optional="false" type="data" size="5497968"/>
    <uses file="FFI_0_1_subfx.sgt" link="input" register="false" transfer="false" optional="false" type="data" size="339181128"/>
    <uses file="FFI_0_1_subfy.sgt" link="input" register="false" transfer="false" optional="false" type="data" size="339181128"/>
    <uses file="Seismogram_FFI_0_1_ID00007.grm" link="output" register="false" transfer="false" optional="false" type="data" size="24000"/>
  </job>
  <job id="ID00008" namespace="CyberShake" name="PeakValCalcOkaya" version="1.0" runtime="0.62">
    <uses file="Seismogram_FFI_0_1_ID00007.grm" link="input" register="false" transfer="false" optional="false" type="data" size="24000"/>
    <uses file="PeakVals_FFI_0_1_ID00007.bsa" link="output" register="false" transfer="false" optional="false" type="data" size="216"/>
  </job>
  <job id="ID00009" namespace="CyberShake" name="SeismogramSynthesis" version="1.0" runtime="57.31">
    <uses file="FFI_0_1_txt.variation-s02932-h07420" link="input" register="true" transfer="true" optional="false" type="data" size="3566193"/>
    <uses file="FFI_0_1_subfx.sgt" link="input" register="false" transfer="false" optional="false" type="data" size="297613815"/>
    <uses file="FFI_0_1_subfy.sgt" link="input" register="false" transfer="false" optional="false" type="data" size="297613815"/>
    <uses file="Seismogram_FFI_0_1_ID00009.grm" link="output" register="false" transfer="false" optional="false" type="data" size="24000"/>
  </job>
  <job id="ID00010" namespace="CyberShake" name="PeakValCalcOkaya" version="1.0" runtime="1.56">
    <uses file="Seismogram_FFI_0_1_ID00009.grm" link="input" register="false" transfer="false" optional="false" type="data" size="24000"/>
    <uses file="PeakVals_FFI_0_1_ID00009.bsa" link="output" register="false" transfer="false" optional="false" type="data" size="216"/>
  </job>
  <job id="ID00011" namespace="CyberShake" name="SeismogramSynthesis" version="1.0" runtime="49.96">
    <uses file="FFI_0_1_txt.variation-s04823-h07935" link="input" register="true" transfer="true" optional="false" type="data" size="3312248"/>
    <uses file="FFI_0_1_subfx.sgt" link="input" register="false" transfer="false" optional="false" type="data" size="117604307"/>
    <uses file="FFI_0_1_subfy.sgt" link="input" register="false" transfer="false" optional="false" type="data" size="117604307"/>
    <uses file="Seismogram_FFI_0_1_ID00011.grm" link="output" register="false" transfer="false" optional="false" type="data" size="24000"/>
  </job>
  <job id="ID00012" namespace="CyberShake" name="PeakValCalcOkaya" version="1.0" runtime="0.59">
    <uses file="Seismogram_FFI_0_1_ID00011.grm" link="input" register="false" transfer="false" optional="false" type="data" size="24000"/>
    <uses file="PeakVals_FFI_0_1_ID00011.bsa" link="output" register="false" transfer="false" optional="false" type="data" size="216"/>
  </job>
  <job id="ID00013" namespace="CyberShake" name="SeismogramSynthesis" version="1.0" runtime="28.60">
    <uses file="FFI_0_1_txt.variation-s05454-h04132" link="input" register="true" transfer="true" optional="false" type="data" size="4199153"/>
    <uses file="FFI_0_1_subfx.sgt" link="input" register="false" transfer="false" optional="false" type="data" size="172148254"/>
    <uses file="FFI_0_1_subfy.sgt" link="input" register="false" transfer="false" optional="false" type="data" size="172148254"/>
    <uses file="Seismogram_FFI_0_1_ID00013.grm" link="output" register="false" transfer="false" optional="false" type="data" size="24000"/>
  </job>
  <job id="ID00014" namespace="CyberShake" name="PeakValCalcOkaya" version="1.0" runtime="1.35">
    <uses file="Seismogram_FFI_0_1_ID00013.grm" link="input" register="false" transfer="false" optional="false" type="data" size="24000"/>
    <uses file="PeakVals_FFI_0_1_ID00013.bsa" link="output" register="false" transfer="false" optional="false" type="data" size="216"/>
  </job>
  <job id="ID00015" namespace="CyberShake" name="SeismogramSynthesis" version="1.0" runtime="43.47">
    <uses file="FFI_0_1_txt.variation-s05834-h08513" link="input" register="true" transfer="true" optional="false" type="data" size="4840258"/>
    <uses file="FFI_0_1_subfx.sgt" link="input" register="false" transfer="false" optional="false" type="data" size="296104501"/>
    <uses file="FFI_0_1_subfy.sgt" link="input" register="false" transfer="false" optional="false" type="data" size="296104501"/>
    <uses file="Seismogram_FFI_0_1_ID00015.grm" link="output" register="false" transfer="false" optional="false" type="data" size="24000"/>
  </job>
  <job id="ID00016" namespace="CyberShake" name="PeakValCalcOkaya" version="1.0" runtime="0.73">
    <uses file="Seismogram_FFI_0_1_ID00015.grm" link="input" register="false" transfer="false" optional="false" type="data" size="24000"/>
    <uses file="PeakVals_FFI_0_1_ID00015.bsa" link="output" register="false" transfer="false" optional="false" type="data" size="216"/>
  </job>
  <job id="ID00017" namespace="CyberShake" name="SeismogramSynthesis" version="1.0" runtime="47.43">
    <uses file="FFI_0_1_txt.variation-s02962-h00264" link="input" register="true" transfer="true" optional="false" type="data" size="4192669"/>
    <uses file="FFI_0_1_subfx.sgt" link="input" register="false" transfer="false" optional="false" type="data" size="328250544"/>
    <uses file="FFI_0_1_subfy.sgt" link="input" register="false" transfer="false" optional="false" type="data" size="328250544"/>
    <uses file="Seismogram_FFI_0_1_ID00017.grm" link="output" register="false" transfer="false" optional="false" type="data" size="24000"/>
  </job>
  <job id="ID00018" namespace="CyberShake" name="PeakValCalcOkaya" version="1.0" runtime="0.56">
    <uses file="Seismogram_FFI_0_1_ID00017.grm" link="input" register="false" transfer="false" optional="false" type="data" size="24000"/>
    <uses file="PeakVals_FFI_0_1_ID00017.bsa" link="output" register="false" transfer="false" optional="false" type="data" size="216"/>
  </job>
  <job id="ID00019" namespace="CyberShake" name="SeismogramSynthesis" version="1.0" runtime="46.70">
    <uses file="FFI_0_1_txt.variation-s07257-h02672" link="input" register="true" transfer="true" optional="false" type="data" size="3944435"/>
    <uses file="FFI_0_1_subfx.sgt" link="input" register="false" transfer="false" optional="false" type="data" size="315520632"/>
    <uses file="FFI_0_1_subfy.sgt" link="input" register="false" transfer="false" optional="false" type="data" size="315520632"/>
    <uses file="Seismogram_FFI_0_1_ID00019.grm" link="output" register="false" transfer="false" optional="false" type="data" size="24000"/>
  </job>
  <job id="ID00020" namespace="CyberShake" name="PeakValCalcOkaya" version="1.0" runtime="1.46">
    <uses file="Seismogram_FFI_0_1_ID00019.grm" link="input" register="false" transfer="false" optional="false" type="data" size="24000"/>
    <uses file="PeakVals_FFI_0_1_ID00019.bsa" link="output" register="false" transfer="false" optional="false" type="data" size="216"/>
  </job>
  <job id="ID00021" namespace="CyberShake" name="SeismogramSynthesis" version="1.0" runtime="54.72">
    <uses file="FFI_0_1_txt.variation-s05013-h06302" link="input" register="true" transfer="true" optional="false" type="data" size="5071188"/>
    <uses file="FFI_0_1_subfx.sgt" link="input" register="false" transfer="false" optional="false" type="data" size="174570490"/>
    <uses file="FFI_0_1_subfy.sgt" link="input" register="false" transfer="false" optional="false" type="data" size="174570490"/>
    <uses file="Seismogram_FFI_0_1_ID00021.grm" link="output" register="false" transfer="false" optional="false" type="data" size="24000"/>
  </job>
  <job id="ID00022" namespace="CyberShake" name="PeakValCalcOkaya" version="1.0" runtime="1.31">
    <uses file="Seismogram_FFI_0_1_ID00021.grm" link="input" register="false" transfer="false" optional="false" type="data" size="24000"/>
    <uses file="PeakVals_FFI_0_1_ID00021.bsa" link="output" register="false" transfer="false" optional="false" type="data" size="216"/>
  </job>
  <job id="ID00023" namespace="CyberShake" name="SeismogramSynthesis" version="1.0" runtime="39.62">
    <uses file="FFI_0_1_txt.variation-s06925-h01869" link="input" register="true" transfer="true" optional="false" type="data" size="2663547"/>
    <uses file="FFI_0_1_subfx.sgt" link="input" register="false" transfer="false" optional="false" type="data" size="248015123"/>
    <uses file="FFI_0_1_subfy.sgt" link="input" register="false" transfer="false" optional="false" type="data" size="248015123"/>
    <uses file="Seismogram_FFI_0_1_ID00023.grm" link="output" register="false" transfer="false" optional="false" type="data" size="24000"/>
  </job>
  <job id="ID00024" namespace="CyberShake" name="PeakValCalcOkaya" version="1.0" runtime="0.93">
    <uses file="Seismogram_FFI_0_1_ID00023.grm" link="input" register="false" transfer="false" optional="false" type="data" size="24000"/>
    <uses file="PeakVals_FFI_0_1_ID00023.bsa" link="output" register="false" transfer="false" optional="false" type="data" size="216"/>
  </job>
<!-- part 3: list of control-flow dependencies (may be empty) -->
  <child ref="ID00000">
    <parent ref="ID00006"/>
    <parent ref="ID00016"/>
    <parent ref="ID00004"/>
    <parent ref="ID00014"/>
    <parent ref="ID00008"/>
    <parent ref="ID00018"/>
    <parent ref="ID00020"/>
    <parent ref="ID00024"/>
    <parent ref="ID00012"/>
    <parent ref="ID00022"/>
    <parent ref="ID00010"/>
  </child>
  <child ref="ID00001">
    <parent ref="ID00017"/>
    <parent ref="ID00005"/>
    <parent ref="ID00015"/>
    <parent ref="ID00003"/>
    <parent ref="ID00009"/>
    <parent ref="ID00019"/>
    <parent ref="ID00007"/>
    <parent ref="ID00013"/>
    <parent ref="ID00023"/>
    <parent ref="ID00011"/>
    <parent ref="ID00021"/>
  </child>
  <child ref="ID00003">
    <parent ref="ID00002"/>
  </child>
  <child ref="ID00004">
    <parent ref="ID00003"/>
  </child>
  <child ref="ID00005">
    <parent ref="ID00002"/>
  </child>
  <child ref="ID00006">
    <parent ref="ID00005"/>
  </child>
  <child ref="ID00007">
    <parent ref="ID00002"/>
  </child>
  <child ref="ID00008">
    <parent ref="ID00007"/>
  </child>
  <child ref="ID00009">
    <parent ref="ID00002"/>
  </child>
  <child ref="ID00010">
    <parent ref="ID00009"/>
  </child>
  <child ref="ID00011">
    <parent ref="ID00002"/>
  </child>
  <child ref="ID00012">
    <parent ref="ID00011"/>
  </child>
  <child ref="ID00013">
    <parent ref="ID00002"/>
  </child>
  <child ref="ID00014">
    <parent ref="ID00013"/>
  </child>
  <child ref="ID00015">
    <parent ref="ID00002"/>
  </child>
  <child ref="ID00016">
    <parent ref="ID00015"/>
  </child>
  <child ref="ID00017">
    <parent ref="ID00002"/>
  </child>
  <child ref="ID00018">
    <parent ref="ID00017"/>
  </child>
  <child ref="ID00019">
    <parent ref="ID00002"/>
  </child>
  <child ref="ID00020">
    <parent ref="ID00019"/>
  </child>
  <child ref="ID00021">
    <parent ref="ID00002"/>
  </child>
  <child ref="ID00022">
    <parent ref="ID00021"/>
  </child>
  <child ref="ID00023">
    <parent ref="ID00002"/>
  </child>
  <child ref="ID00024">
    <parent ref="ID00023"/>
  </child>
</adag>
